vidiopy/Clip.py
vidiopy/__init__.py
vidiopy/__version__.py
vidiopy/config.py
vidiopy/decorators.py
vidiopy/editor.py
vidiopy/audio/AudioClip.py
vidiopy/audio/fx/__init__.py
vidiopy/binary/folder_info.md
vidiopy/video/ImageClips.py
vidiopy/video/ImageSequenceClip.py
vidiopy/video/VideoClip.py
vidiopy/video/VideoFileClip.py
vidiopy/video/mixing_clip.py
vidiopy/video/preview.py
vidiopy/video/fx/__init__.py
vidiopy/video/fx/accel_decel.py
vidiopy/video/fx/crop.py
vidiopy/video/fx/filters.py
vidiopy-0.3.12.dist-info/LICENSE
vidiopy-0.3.12.dist-info/METADATA
vidiopy-0.3.12.dist-info/WHEEL
vidiopy-0.3.12.dist-info/top_level.txt
vidiopy-0.3.12.dist-info/RECORD
