Metadata-Version: 2.1
Name: vidiopy
Version: 0.3.12
Summary: An Video Editing Library Similar to Moviepy.
Home-page: https://github.com/SohamTilekar/vidiopy
Author: Soham Tilekar
Author-email: sohamtilekar233@gamil.com
License: MIT License
Project-URL: Homepage, https://github.com/SohamTilekar/vidiopy/
Project-URL: Source, https://github.com/SohamTilekar/vidiopy/
Project-URL: Tracker, https://github.com/SohamTilekar/vidiopy/issues
Classifier: Programming Language :: Python :: 3.12
Classifier: Development Status :: 3 - Alpha
Classifier: Environment :: Win32 (MS Windows)
Classifier: License :: OSI Approved :: MIT No Attribution License (MIT-0)
Classifier: License :: OSI Approved :: MIT License
Classifier: Operating System :: Microsoft :: Windows :: Windows 10
Classifier: Topic :: Multimedia :: Graphics :: Editors
Classifier: Topic :: Multimedia
Classifier: Topic :: Multimedia :: Sound/Audio :: Editors
Classifier: Topic :: Multimedia :: Sound/Audio
Classifier: Topic :: Multimedia :: Video
Classifier: Topic :: Software Development :: Libraries :: Python Modules
Classifier: Topic :: Software Development :: Version Control :: Git
Requires-Python: >=3.11, <=3.12.2
License-File: LICENSE
Requires-Dist: rich >=13.7.0
Requires-Dist: numpy >=1.24.4
Requires-Dist: ffmpegio >=0.9.0
Requires-Dist: pillow >=10.2.0
